xy_request_handler_api/Api.py
xy_request_handler_api/__init__.py
xy_request_handler_api-1.0.0.dist-info/LICENSE
xy_request_handler_api-1.0.0.dist-info/METADATA
xy_request_handler_api-1.0.0.dist-info/WHEEL
xy_request_handler_api-1.0.0.dist-info/top_level.txt
xy_request_handler_api-1.0.0.dist-info/RECORD
